remotion_lambda/__init__.py
remotion_lambda/exception.py
remotion_lambda/models.py
remotion_lambda/remotionclient.py
remotion_lambda/version.py
tests/__init__.py
tests/conftest.py
tests/constants.py
tests/test_get_render_progress_client.py
tests/test_large_payload_compression.py
tests/test_remotion_client.py
tests/test_render_client_render_media.py
tests/test_render_client_render_still.py
remotion_lambda-4.0.415.dist-info/LICENSE
remotion_lambda-4.0.415.dist-info/METADATA
remotion_lambda-4.0.415.dist-info/WHEEL
remotion_lambda-4.0.415.dist-info/top_level.txt
remotion_lambda-4.0.415.dist-info/RECORD
