Metadata-Version: 2.1
Name: remotion-lambda
Version: 4.0.415
Summary: Remotion Lambda client
Home-page: https://github.com/remotion-dev/remotion/tree/main/packages/lambda-python
Author: Jonny Burger
Author-email: jonny@remotion.dev
Requires-Python: >=3.6
License-File: LICENSE
Requires-Dist: boto3<2.0.0,>=1.34.23
